sphinx_bazel-0.1.6-py3.8-nspkg.pth
sphinxcontrib/sphinx_bazel/__init__.py
sphinxcontrib/sphinx_bazel/sphinx_bazel.py
sphinxcontrib/sphinx_bazel/autobazel/__init__.py
sphinxcontrib/sphinx_bazel/autobazel/common.py
sphinxcontrib/sphinx_bazel/domain/__init__.py
sphinxcontrib/sphinx_bazel/domain/domain.py
sphinxcontrib/sphinx_bazel/domain/object.py
sphinxcontrib/sphinx_bazel/domain/util.py
sphinxcontrib/sphinx_bazel/domain/workspace.py
sphinx_bazel-0.1.6.dist-info/AUTHORS
sphinx_bazel-0.1.6.dist-info/LICENSE
sphinx_bazel-0.1.6.dist-info/METADATA
sphinx_bazel-0.1.6.dist-info/WHEEL
sphinx_bazel-0.1.6.dist-info/namespace_packages.txt
sphinx_bazel-0.1.6.dist-info/top_level.txt
sphinx_bazel-0.1.6.dist-info/RECORD
