Metadata-Version: 2.1
Name: sphinx-bazel
Version: 0.1.6
Summary: Sphinx bazel extension to include content from bazel files.
Home-page: http://github.com/useblocks/sphinx-bazel
Author: team useblocks
Author-email: info@useblocks.com
License: Apache 2.0
Download-URL: http://pypi.python.org/pypi/sphinx-bazel
Platform: any
Classifier: Development Status :: 3 - Alpha
Classifier: Intended Audience :: Developers
Classifier: License :: OSI Approved :: Apache Software License
Classifier: Operating System :: OS Independent
Classifier: Programming Language :: Python
Classifier: Programming Language :: Python :: 2
Classifier: Programming Language :: Python :: 2.7
Classifier: Programming Language :: Python :: 3
Classifier: Programming Language :: Python :: 3.5
Classifier: Programming Language :: Python :: 3.6
Classifier: Programming Language :: Python :: 3.7
Classifier: Topic :: Documentation
Classifier: Topic :: Utilities
Requires-Dist: Sphinx (<2) ; python_version < "3.5"
Requires-Dist: Sphinx (<3) ; python_version < "3.6"
Requires-Dist: Sphinx ; python_version >= "3.6"
